waves/__init__.py
waves/amount_pb2.py
waves/block_pb2.py
waves/events/events_pb2.py
waves/events/grpc/blockchain_updates_pb2.py
waves/invoke_script_result_pb2.py
waves/lang/dapp_meta_pb2.py
waves/node/grpc/accounts_api_pb2.py
waves/node/grpc/assets_api_pb2.py
waves/node/grpc/blockchain_api_pb2.py
waves/node/grpc/blocks_api_pb2.py
waves/node/grpc/transactions_api_pb2.py
waves/order_pb2.py
waves/recipient_pb2.py
waves/reward_share_pb2.py
waves/state_snapshot_pb2.py
waves/transaction_pb2.py
waves/transaction_state_snapshot_pb2.py
pywaves_protobuf-1.5.2.post1.dist-info/LICENSE
pywaves_protobuf-1.5.2.post1.dist-info/METADATA
pywaves_protobuf-1.5.2.post1.dist-info/WHEEL
pywaves_protobuf-1.5.2.post1.dist-info/RECORD
